chroma_repository/__init__.py
chroma_repository/chroma_repository.py
chroma_repository/icustom_retriever.py
chroma_repository/ivector_repository.py
chroma_repository/multi_search_retriever.py
chroma_repository/similarity_search_retriever.py
chroma_repository/small_chunks_search_retriever.py
chromarepository-1.0.5.dist-info/licenses/LICENSE
chromarepository-1.0.5.dist-info/METADATA
chromarepository-1.0.5.dist-info/WHEEL
chromarepository-1.0.5.dist-info/top_level.txt
chromarepository-1.0.5.dist-info/RECORD
