Metadata-Version: 2.4
Name: chromarepository
Version: 1.0.5
Summary: ChromaRepository is a wrapper around Chroma Vector Repository
Author-email: DarthLinuxer <chaves.camilo@gmail.com>
License: MIT
Project-URL: Homepage, https://github.com/darthlinuxer/AI
Classifier: Programming Language :: Python :: 3
Classifier: Programming Language :: Python :: 3.8
Classifier: Programming Language :: Python :: 3.9
Classifier: Programming Language :: Python :: 3.10
Classifier: Programming Language :: Python :: 3.11
Classifier: Programming Language :: Python :: 3.12
Classifier: Operating System :: OS Independent
Classifier: Development Status :: 5 - Production/Stable
Classifier: Intended Audience :: Developers
Requires-Python: >=3.8
License-File: LICENSE
Dynamic: license-file
